conectividadeapp/__init__.py
conectividadeapp/admin.py
conectividadeapp/apps.py
conectividadeapp/filters.py
conectividadeapp/forms.py
conectividadeapp/models.py
conectividadeapp/navigation.py
conectividadeapp/tables.py
conectividadeapp/template_content.py
conectividadeapp/tests.py
conectividadeapp/urls.py
conectividadeapp/views.py
conectividadeapp/__pycache__/__init__.cpython-38.pyc
conectividadeapp/__pycache__/admin.cpython-38.pyc
conectividadeapp/__pycache__/filters.cpython-38.pyc
conectividadeapp/__pycache__/forms.cpython-38.pyc
conectividadeapp/__pycache__/models.cpython-38.pyc
conectividadeapp/__pycache__/navigation.cpython-38.pyc
conectividadeapp/__pycache__/tables.cpython-38.pyc
conectividadeapp/__pycache__/template_content.cpython-38.pyc
conectividadeapp/__pycache__/urls.cpython-38.pyc
conectividadeapp/__pycache__/views.cpython-38.pyc
conectividadeapp/api/__init__.py
conectividadeapp/api/nested_serializers.py
conectividadeapp/api/serializers.py
conectividadeapp/api/urls.py
conectividadeapp/api/views.py
conectividadeapp/api/__pycache__/__init__.cpython-38.pyc
conectividadeapp/api/__pycache__/nested_serializers.cpython-38.pyc
conectividadeapp/api/__pycache__/serializers.cpython-38.pyc
conectividadeapp/api/__pycache__/urls.cpython-38.pyc
conectividadeapp/api/__pycache__/views.cpython-38.pyc
conectividadeapp/migrations/0001_initial.py
conectividadeapp/migrations/0002_auto_20210126_1849.py
conectividadeapp/migrations/0003_auto_20210225_1739.py
conectividadeapp/migrations/__init__.py
conectividadeapp/migrations/__pycache__/0001_initial.cpython-38.pyc
conectividadeapp/migrations/__pycache__/0002_auto_20210126_1849.cpython-38.pyc
conectividadeapp/migrations/__pycache__/0003_auto_20210225_1739.cpython-38.pyc
conectividadeapp/migrations/__pycache__/__init__.cpython-38.pyc
conectividadeapp/templates/conectividadeapp/activities_history_list.html
conectividadeapp/templates/conectividadeapp/activity_details.html
conectividadeapp-1.1.2.dist-info/LICENSE
conectividadeapp-1.1.2.dist-info/METADATA
conectividadeapp-1.1.2.dist-info/WHEEL
conectividadeapp-1.1.2.dist-info/top_level.txt
conectividadeapp-1.1.2.dist-info/RECORD
