Metadata-Version: 2.1
Name: conectividadeapp
Version: 1.1.2
Summary: Plugin de conectividade para o Netbox
Home-page: https://github.com/ufrn-netbox/conectividadeapp
Author: Johnny, Avando, Eduardo, Rary, Thiago
License: Apache 2.0
Platform: UNKNOWN
Requires-Dist: django-simple-history
